[
  {
    "ContainingType": "QuizApp.Api.Controllers.AuthController",
    "Method": "Login",
    "RelativePath": "api/Auth/login",
    "HttpMethod": "POST",
    "IsController": true,
    "Order": 0,
    "Parameters": [
      {
        "Name": "model",
        "Type": "QuizApp.Core.ViewModels.LoginViewModel",
        "IsRequired": true
      }
    ],
    "ReturnTypes": [
      {
        "Type": "QuizApp.Core.ViewModels.AuthResponseViewModel",
        "MediaTypes": [
          "text/plain",
          "application/json",
          "text/json"
        ],
        "StatusCode": 200
      }
    ]
  },
  {
    "ContainingType": "QuizApp.Api.Controllers.AuthController",
    "Method": "Register",
    "RelativePath": "api/Auth/register",
    "HttpMethod": "POST",
    "IsController": true,
    "Order": 0,
    "Parameters": [
      {
        "Name": "model",
        "Type": "QuizApp.Core.ViewModels.RegisterViewModel",
        "IsRequired": true
      }
    ],
    "ReturnTypes": [
      {
        "Type": "QuizApp.Core.ViewModels.AuthResponseViewModel",
        "MediaTypes": [
          "text/plain",
          "application/json",
          "text/json"
        ],
        "StatusCode": 200
      }
    ]
  },
  {
    "ContainingType": "QuizApp.Api.Controllers.GameController",
    "Method": "GetGameSession",
    "RelativePath": "api/Game/{id}",
    "HttpMethod": "GET",
    "IsController": true,
    "Order": 0,
    "Parameters": [
      {
        "Name": "id",
        "Type": "System.Int32",
        "IsRequired": true
      }
    ],
    "ReturnTypes": [
      {
        "Type": "QuizApp.Core.Models.GameSession",
        "MediaTypes": [
          "text/plain",
          "application/json",
          "text/json"
        ],
        "StatusCode": 200
      }
    ]
  },
  {
    "ContainingType": "QuizApp.Api.Controllers.GameController",
    "Method": "GetLeaderboard",
    "RelativePath": "api/Game/{id}/leaderboard",
    "HttpMethod": "GET",
    "IsController": true,
    "Order": 0,
    "Parameters": [
      {
        "Name": "id",
        "Type": "System.Int32",
        "IsRequired": true
      }
    ],
    "ReturnTypes": [
      {
        "Type": "System.Collections.Generic.IEnumerable\u00601[[QuizApp.Core.Models.Player, QuizApp.Core, Version=1.0.0.0, Culture=neutral, PublicKeyToken=null]]",
        "MediaTypes": [
          "text/plain",
          "application/json",
          "text/json"
        ],
        "StatusCode": 200
      }
    ]
  },
  {
    "ContainingType": "QuizApp.Api.Controllers.GameController",
    "Method": "GetNextQuestion",
    "RelativePath": "api/Game/{id}/next-question",
    "HttpMethod": "POST",
    "IsController": true,
    "Order": 0,
    "Parameters": [
      {
        "Name": "id",
        "Type": "System.Int32",
        "IsRequired": true
      }
    ],
    "ReturnTypes": [
      {
        "Type": "QuizApp.Core.Models.Question",
        "MediaTypes": [
          "text/plain",
          "application/json",
          "text/json"
        ],
        "StatusCode": 200
      }
    ]
  },
  {
    "ContainingType": "QuizApp.Api.Controllers.GameController",
    "Method": "SubmitAnswer",
    "RelativePath": "api/Game/answer",
    "HttpMethod": "POST",
    "IsController": true,
    "Order": 0,
    "Parameters": [
      {
        "Name": "playerAnswer",
        "Type": "QuizApp.Core.Models.PlayerAnswer",
        "IsRequired": true
      }
    ],
    "ReturnTypes": [
      {
        "Type": "QuizApp.Core.Models.PlayerAnswer",
        "MediaTypes": [
          "text/plain",
          "application/json",
          "text/json"
        ],
        "StatusCode": 200
      }
    ]
  },
  {
    "ContainingType": "QuizApp.Api.Controllers.GameController",
    "Method": "GetPlayerAnswer",
    "RelativePath": "api/Game/answer/{id}",
    "HttpMethod": "GET",
    "IsController": true,
    "Order": 0,
    "Parameters": [
      {
        "Name": "id",
        "Type": "System.Int32",
        "IsRequired": true
      }
    ],
    "ReturnTypes": [
      {
        "Type": "QuizApp.Core.Models.PlayerAnswer",
        "MediaTypes": [
          "text/plain",
          "application/json",
          "text/json"
        ],
        "StatusCode": 200
      }
    ]
  },
  {
    "ContainingType": "QuizApp.Api.Controllers.GameController",
    "Method": "JoinGame",
    "RelativePath": "api/Game/join",
    "HttpMethod": "POST",
    "IsController": true,
    "Order": 0,
    "Parameters": [
      {
        "Name": "gameCode",
        "Type": "System.String",
        "IsRequired": false
      },
      {
        "Name": "playerName",
        "Type": "System.String",
        "IsRequired": false
      }
    ],
    "ReturnTypes": [
      {
        "Type": "QuizApp.Core.Models.Player",
        "MediaTypes": [
          "text/plain",
          "application/json",
          "text/json"
        ],
        "StatusCode": 200
      }
    ]
  },
  {
    "ContainingType": "QuizApp.Api.Controllers.GameController",
    "Method": "GetPlayer",
    "RelativePath": "api/Game/player/{id}",
    "HttpMethod": "GET",
    "IsController": true,
    "Order": 0,
    "Parameters": [
      {
        "Name": "id",
        "Type": "System.Int32",
        "IsRequired": true
      }
    ],
    "ReturnTypes": [
      {
        "Type": "QuizApp.Core.Models.Player",
        "MediaTypes": [
          "text/plain",
          "application/json",
          "text/json"
        ],
        "StatusCode": 200
      }
    ]
  },
  {
    "ContainingType": "QuizApp.Api.Controllers.GameController",
    "Method": "GetGameSessionByCode",
    "RelativePath": "api/Game/session/{gameCode}",
    "HttpMethod": "GET",
    "IsController": true,
    "Order": 0,
    "Parameters": [
      {
        "Name": "gameCode",
        "Type": "System.String",
        "IsRequired": true
      }
    ],
    "ReturnTypes": [
      {
        "Type": "QuizApp.Core.Models.GameSession",
        "MediaTypes": [
          "text/plain",
          "application/json",
          "text/json"
        ],
        "StatusCode": 200
      }
    ]
  },
  {
    "ContainingType": "QuizApp.Api.Controllers.GameController",
    "Method": "StartGame",
    "RelativePath": "api/Game/start/{quizId}",
    "HttpMethod": "POST",
    "IsController": true,
    "Order": 0,
    "Parameters": [
      {
        "Name": "quizId",
        "Type": "System.Int32",
        "IsRequired": true
      }
    ],
    "ReturnTypes": [
      {
        "Type": "QuizApp.Core.Models.GameSession",
        "MediaTypes": [
          "text/plain",
          "application/json",
          "text/json"
        ],
        "StatusCode": 200
      }
    ]
  },
  {
    "ContainingType": "QuizApp.Api.Controllers.QuizController",
    "Method": "GetQuizzes",
    "RelativePath": "api/Quiz",
    "HttpMethod": "GET",
    "IsController": true,
    "Order": 0,
    "Parameters": [],
    "ReturnTypes": [
      {
        "Type": "System.Collections.Generic.IEnumerable\u00601[[QuizApp.Core.Models.Quiz, QuizApp.Core, Version=1.0.0.0, Culture=neutral, PublicKeyToken=null]]",
        "MediaTypes": [
          "text/plain",
          "application/json",
          "text/json"
        ],
        "StatusCode": 200
      }
    ]
  },
  {
    "ContainingType": "QuizApp.Api.Controllers.QuizController",
    "Method": "CreateQuiz",
    "RelativePath": "api/Quiz",
    "HttpMethod": "POST",
    "IsController": true,
    "Order": 0,
    "Parameters": [
      {
        "Name": "viewModel",
        "Type": "QuizApp.Core.ViewModels.QuizViewModel",
        "IsRequired": true
      }
    ],
    "ReturnTypes": [
      {
        "Type": "QuizApp.Core.Models.Quiz",
        "MediaTypes": [
          "text/plain",
          "application/json",
          "text/json"
        ],
        "StatusCode": 200
      }
    ]
  },
  {
    "ContainingType": "QuizApp.Api.Controllers.QuizController",
    "Method": "GetQuiz",
    "RelativePath": "api/Quiz/{id}",
    "HttpMethod": "GET",
    "IsController": true,
    "Order": 0,
    "Parameters": [
      {
        "Name": "id",
        "Type": "System.Int32",
        "IsRequired": true
      }
    ],
    "ReturnTypes": [
      {
        "Type": "QuizApp.Core.Models.Quiz",
        "MediaTypes": [
          "text/plain",
          "application/json",
          "text/json"
        ],
        "StatusCode": 200
      }
    ]
  },
  {
    "ContainingType": "QuizApp.Api.Controllers.QuizController",
    "Method": "UpdateQuiz",
    "RelativePath": "api/Quiz/{id}",
    "HttpMethod": "PUT",
    "IsController": true,
    "Order": 0,
    "Parameters": [
      {
        "Name": "id",
        "Type": "System.Int32",
        "IsRequired": true
      },
      {
        "Name": "viewModel",
        "Type": "QuizApp.Core.ViewModels.QuizViewModel",
        "IsRequired": true
      }
    ],
    "ReturnTypes": []
  },
  {
    "ContainingType": "QuizApp.Api.Controllers.QuizController",
    "Method": "DeleteQuiz",
    "RelativePath": "api/Quiz/{id}",
    "HttpMethod": "DELETE",
    "IsController": true,
    "Order": 0,
    "Parameters": [
      {
        "Name": "id",
        "Type": "System.Int32",
        "IsRequired": true
      }
    ],
    "ReturnTypes": []
  }
]