{"GlobalPropertiesHash":"XnMbWWx/e2q32GUl02quKGquyOpymGBw4A4tD3WdzJU=","FingerprintPatternsHash":"gq3WsqcKBUGTSNle7RKKyXRIwh7M8ccEqOqYvIzoM04=","PropertyOverridesHash":"8ZRc1sGeVrPBx4lD717BgRaQekyh78QKV9SKsdt638U=","InputHashes":["wP1aHJnuAg4FNsWDYxgawcK054jbDuazfsMMfjE7qKQ=","nrQFq\u002BQdWuSp93L0EvQ73nXgHMPFYth556mLiHqQ5/U=","9q/Wv\u002B8dtEMBtIbeJp6\u002BtkrZ9X7jaz6PSs1d7RvAVo8="],"CachedAssets":{"wP1aHJnuAg4FNsWDYxgawcK054jbDuazfsMMfjE7qKQ=":{"Identity":"C:\\Users\\Ivan\\Desktop\\ARDENT-Project\\QuizApp\\QuizApp.Api\\wwwroot\\auth-test.html","SourceId":"QuizApp.Api","SourceType":"Discovered","ContentRoot":"C:\\Users\\Ivan\\Desktop\\ARDENT-Project\\QuizApp\\QuizApp.Api\\wwwroot\\","BasePath":"_content/QuizApp.Api","RelativePath":"auth-test#[.{fingerprint}]?.html","AssetKind":"All","AssetMode":"All","AssetRole":"Primary","AssetMergeBehavior":null,"AssetMergeSource":"","RelatedAsset":null,"AssetTraitName":null,"AssetTraitValue":null,"Fingerprint":"4n2v3hj70q","Integrity":"INYhYfgcO\u002B4tLySUxy41kj/OrFcyc7O09SuxtkhksRA=","CopyToOutputDirectory":"Never","CopyToPublishDirectory":"PreserveNewest","OriginalItemSpec":"wwwroot\\auth-test.html","FileLength":2768,"LastWriteTime":"2025-06-08T18:07:16.386499+00:00"}},"CachedCopyCandidates":{}}